README.rst
setup.cfg
setup.py
flask_transfer/__init__.py
flask_transfer/exc.py
flask_transfer/transfer.py
flask_transfer/validators.py
flask_transfer.egg-info/PKG-INFO
flask_transfer.egg-info/SOURCES.txt
flask_transfer.egg-info/dependency_links.txt
flask_transfer.egg-info/not-zip-safe
flask_transfer.egg-info/requires.txt
flask_transfer.egg-info/top_level.txt