Metadata-Version: 1.1
Name: flask-transfer
Version: 0.0.1
Summary: Validate and process file uploads in Flask easily
Home-page: https://github.com/justanr/Flask-Transfer
Author: Alec Nikolas Reiter
Author-email: alecreiter@gmail.com
License: MIT
Keywords: flask,uploads
Platform: UNKNOWN
Classifier: Development Status :: 3 - Alpha
Classifier: Framework :: Flask
Classifier: Environment :: Web Environment
Classifier: Intended Audience :: Developers
Classifier: License :: OSI Approved :: MIT License
Classifier: Programming Language :: Python :: 2.7
Classifier: Programming Language :: Python :: 3.4
